[
  {
    "id": "gdg-cee-summit-2016-announced",
    "title": "GDG CEE Summit 2016 Announced",
    "posted": "2016-08-01",
    "primaryColor": "#FF9800",
    "secondaryColor": "#FF9800",
    "image": "/images/posts/announce.jpg",
    "brief": "GDG CEE Summit is a place for organizers to meet and connect with neighbor organizers and share their experiences, so prepare for a weekend full of hard work and surprises!"
  },
  {
    "id": "present-your-group",
    "title": "Present your group",
    "posted": "2016-09-20",
    "primaryColor": "#673AB7",
    "secondaryColor": "#673AB7",
    "image": "/images/posts/present-your-group.jpg",
    "brief": "The core idea of the event is to get introduced to all neighbour organizers and make new friends, so _each attending GDG chapter must prepare a small presentation_ to introduce themselves."
  }
]
