[{
    "title": "Template creator",
    "logos": [{
        "name": "GDG Lviv",
        "url": "https://plus.google.com/102444623953913144164",
        "logoUrl": "../images/partners/gdg-lviv.svg",
        "width": 170
    }]
}, {
    "title": "General partner",
    "logos": [{
        "name": "Google",
        "url": "https://www.google.com.ua/intl/en/about/",
        "logoUrl": "../images/partners/google.svg"
    },{
        "name": "GDG[x]",
        "url": "https://github.com/gdg-x",
        "logoUrl": "../images/partners/gdg-x.svg"
    },{
        "name": "Google",
        "url": "https://www.google.com.ua/intl/en/about/",
        "logoUrl": "../images/partners/google.svg"
    },{
        "name": "GDG[x]",
        "url": "https://github.com/gdg-x",
        "logoUrl": "../images/partners/gdg-x.svg"
    },{
        "name": "Google",
        "url": "https://www.google.com.ua/intl/en/about/",
        "logoUrl": "../images/partners/google.svg"
    },{
        "name": "GDG[x]",
        "url": "https://github.com/gdg-x",
        "logoUrl": "../images/partners/gdg-x.svg"
    },{
        "name": "Google",
        "url": "https://www.google.com.ua/intl/en/about/",
        "logoUrl": "../images/partners/google.svg"
    },{
        "name": "GDG[x]",
        "url": "https://github.com/gdg-x",
        "logoUrl": "../images/partners/gdg-x.svg"
    },{
        "name": "Google",
        "url": "https://www.google.com.ua/intl/en/about/",
        "logoUrl": "../images/partners/google.svg"
    },{
        "name": "GDG[x]",
        "url": "https://github.com/gdg-x",
        "logoUrl": "../images/partners/gdg-x.svg"
    },{
        "name": "Google",
        "url": "https://www.google.com.ua/intl/en/about/",
        "logoUrl": "../images/partners/google.svg"
    }]
}]
