{
    "1": {
        "id": 1,
        "featured": true,
        "name": "Takuo Suzuki",
        "title": "Developer Relation, Reginal Lead",
        "company": "Google Japan",
        "companyLogo": "/images/logos/google.svg",
        "country": "Tokyo, Japan",
        "photoUrl": "",
        "shortBio": "Takuo is a Developer Relation, Regional Lead at Google, currently focused on helping developers with Google technologies...",
        "bio": "Takuo is a Developer Relation Regional Lead at Google, currently focused on helping developers with Google technologies.",
        "tags": [
            "Startups",
            "UI/UX",
            "Data Visualization"
        ],
        "badges": [

        ],
        "socials": [

        ]
    },
    "2": {
        "id": 2,
        "featured": true,
        "name": "TBD",
        "title": "Googler",
        "company": "Google",
        "companyLogo": "/images/logos/google.svg",
        "country": "TBD",
        "photoUrl": "",
        "shortBio": "TBD",
        "bio": "TBD",
        "tags": [
            "TBD"
        ],
        "badges": [

        ],
        "socials": [

        ]
    },
    "3": {
        "id": 3,
        "featured": true,
        "name": "TBD",
        "title": "TBD",
        "company": "Googler",
        "companyLogo": "/images/logos/google.svg",
        "country": "Changhwa, Taiwan",
        "photoUrl": "",
        "shortBio": "TBD",
        "bio": "TBD",
        "tags": [
            "TBD"
        ],
        "badges": [

        ],
        "socials": [

        ]
    },
    "4": {
        "id": 4,
        "featured": false,
        "name": "張景隆",
        "title": "",
        "company": "",
        "companyLogo": "",
        "country": "Taiwan",
        "photoUrl": "",
        "shortBio": "",
        "bio": "",
        "tags": [
            "iOS",
            "Firebase"
        ],
        "badges": [

        ],
        "socials": [

        ]
    },
    "5": {
        "id": 5,
        "featured": false,
        "name": "Aki",
        "title": "",
        "company": "",
        "companyLogo": "",
        "country": "Taiwan",
        "photoUrl": "",
        "shortBio": "",
        "bio": "",
        "tags": [
            "TBD"
        ],
        "badges": [

        ],
        "socials": [

        ]
    },
    "6": {
        "id": 6,
        "featured": false,
        "name": "Ray Shih",
        "title": "",
        "company": "",
        "companyLogo": "",
        "country": "Taiwan",
        "photoUrl": "",
        "shortBio": "",
        "bio": "",
        "tags": [
            "TBD"
        ],
        "badges": [

        ],
        "socials": [

        ]
    },
    "7": {
        "id": 7,
        "featured": false,
        "name": "Andy",
        "title": "",
        "company": "",
        "companyLogo": "",
        "country": "Taiwan",
        "photoUrl": "",
        "shortBio": "",
        "bio": "",
        "tags": [
            "Cloud"
        ],
        "badges": [

        ],
        "socials": [

        ]
    },
    "8": {
        "id": 8,
        "featured": true,
        "name": "Evan Lin",
        "title": "Cloud Architect",
        "company": "Linker Networks",
        "companyLogo": "",
        "country": "Taipei, Taiwan",
        "photoUrl": "https://scontent-hkg3-1.xx.fbcdn.net/v/t1.0-9/11822616_10205620897855546_701112722031919314_n.jpg?oh=6fc1b93373f451def14aa0b2e6cd61ae&oe=58D09141",
        "shortBio": "Cloud Architect at Linker Networks, Co-organizer of Golang Taiwan User Group.",
        "bio": "Cloud Architect at Linker Networks, Co-organizer of Golang Taiwan User Group.",
        "tags": [
            "Android",
            "iOS",
            "Cloud",
            "Golang",
            "Multimedia"
        ],
        "badges": [
            {
                "name": "Golang Taiwan User Group",
                "description": "Co-organizer",
                "link": ""
            }
        ],
        "socials": [

        ]
    },
    "9": {
        "id": 9,
        "featured": false,
        "name": "Williams",
        "title": "Android Engineer",
        "company": "",
        "companyLogo": "",
        "country": "Taiwan",
        "photoUrl": "",
        "shortBio": "Android enthusiast.",
        "bio": "Currently Android Engineer.",
        "tags": [
            "Android"
        ],
        "badges": [

        ],
        "socials": [

        ]
    },
    "10": {
        "id": 10,
        "featured": true,
        "name": "Araon Lai",
        "title": "",
        "company": "",
        "companyLogo": "",
        "country": "Taipei, Taiwan",
        "photoUrl": "",
        "shortBio": "",
        "bio": "",
        "tags": [
            "Cloud"
        ],
        "badges": [

        ],
        "socials": [

        ]
    },
    "11": {
        "id": 11,
        "featured": true,
        "name": "Akane",
        "title": "UI/UX Designer",
        "company": "",
        "companyLogo": "",
        "country": "Taipei, Taiwan",
        "photoUrl": "",
        "shortBio": "",
        "bio": "",
        "tags": [
            "UI/UX",
            "Prototyping"
        ],
        "badges": [

        ],
        "socials": [

        ]
    },
    "12": {
        "id": 12,
        "featured": true,
        "name": "John Huang / 黃種熙",
        "title": "Director",
        "company": "ASUStek Corporation",
        "companyLogo": "",
        "country": "Taipei, Taiwan",
        "photoUrl": "",
        "shortBio": "",
        "bio": "",
        "tags": [
            "Android",
            "Robotics",
            "Linux"
        ],
        "badges": [
            {
                "name": "ASUStek",
                "description": "ASUStek Corporation",
                "link": ""
            }
        ],
        "socials": [

        ]
    },
    "13": {
        "id": 13,
        "featured": false,
        "name": "陳勇志",
        "title": "",
        "company": "",
        "companyLogo": "",
        "country": "Taipei, Taiwan",
        "photoUrl": "",
        "shortBio": "",
        "bio": "",
        "tags": [
            "Android"
        ],
        "badges": [

        ],
        "socials": [

        ]
    },
    "14": {
        "id": 14,
        "featured": true,
        "name": "Mosky Liu / 劉依語",
        "title": "",
        "company": "",
        "companyLogo": "",
        "country": "Taipei, Taiwan",
        "photoUrl": "",
        "shortBio": "",
        "bio": "",
        "tags": [

        ],
        "badges": [

        ],
        "socials": [

        ]
    },
    "15": {
        "id": 15,
        "featured": true,
        "name": "Cooper",
        "title": "",
        "company": "HTC Corporation / 宏達國際電子",
        "companyLogo": "",
        "country": "Taipei, Taiwan",
        "photoUrl": "",
        "shortBio": "",
        "bio": "",
        "tags": [
            "Android",
            "VR"
        ],
        "badges": [
            {
                "name": "HTC",
                "description": "HTC Corporation / 宏達國際電子",
                "link": "https://www.htc.com"
            }
        ],
        "socials": [

        ]
    },
    "16": {
        "id": 16,
        "featured": true,
        "name": "Cateyes",
        "title": "Android Developer",
        "company": "Taiwan Android Developer Study Group / 台灣 Android 開發者讀書會",
        "companyLogo": "",
        "country": "Taipei, Taiwan",
        "photoUrl": "",
        "shortBio": "TADSG member, Android enthusiast.",
        "bio": "Cateyes is a passionate Android developer and mobile technology evangelist. He is an member of TADSG.",
        "tags": [
            "Android",
            "Firebase"
        ],
        "badges": [
            {
                "name": "TADSG",
                "description": "Member of Taiwan Android Developer Study Group / 台灣 Android 開發者讀書會"
            }
        ],
        "socials": [

        ]
    },
    "17": {
        "id": 17,
        "featured": true,
        "name": "Charlie Tsai",
        "title": "Senior Android Developer",
        "company": "",
        "companyLogo": "",
        "country": "Taipei, Taiwan",
        "photoUrl": "",
        "shortBio": "TADSG Co-organizer, Android enthusiast. Frequent speaker on tech events. Future Googler. Before joining Google, he worked for nVidia Taiwan as an system developer.",
        "bio": "TADSG Co-organizer, Android enthusiast. Frequent speaker on tech events. Future Googler. Before joining Google, he worked for nVidia Taiwan as an system developer.",
        "tags": [
            "Android",
            "Animations",
            "3D Graphics"
        ],
        "badges": [
            {
                "name": "TADSG",
                "description": "Member of Taiwan Android Developer Study Group / 台灣 Android 開發者讀書會"
            }
        ],
        "socials": [

        ]
    },
    "18": {
        "id": 18,
        "featured": true,
        "name": "Takuma Lee",
        "title": "Senior Android Developer",
        "company": "Taiwan Android Developer Study Group / 台灣 Android 開發者讀書會",
        "companyLogo": "",
        "country": "Taipei, Taiwan",
        "photoUrl": "",
        "shortBio": "Founder of TADSG, Android enthusiast.",
        "bio": "Founder of TADSG, Android enthusiast.",
        "tags": [
            "Android"
        ],
        "badges": [
            {
                "name": "TADSG",
                "description": "Founder of Taiwan Android Developer Study Group / 台灣 Android 開發者讀書會創辦人"
            }
        ],
        "socials": [

        ]
    },
    "19": {
        "id": 19,
        "featured": false,
        "name": "Unknown",
        "title": "Unknown",
        "company": "Unknown",
        "companyLogo": "",
        "country": "Unknown",
        "photoUrl": "",
        "shortBio": "Unknown",
        "bio": "Unknown",
        "tags": [
            "Unknown"
        ],
        "badges": [
            {
                "name": "Unknown",
                "description": "Unknown",
                "link": ""
            }
        ],
        "socials": [
            {
                "icon": "twitter",
                "name": "Twitter",
                "link": ""
            }
        ]
    }
}
